{
  "_class": "shapePath",
  "booleanOperation": -1,
  "do_objectID": "D8309096-C36F-479B-9B24-0F7F5D446F39",
  "edited": true,
  "exportOptions": {
    "_class": "exportOptions",
    "exportFormats": [
    ],
    "includedLayerIds": [
    ],
    "layerOptions": 0,
    "shouldTrim": false
  },
  "frame": {
    "_class": "rect",
    "constrainProportions": false,
    "height": 15.73620515221018,
    "width": 12.8673346092585,
    "x": 0,
    "y": 0
  },
  "isFlippedHorizontal": false,
  "isFlippedVertical": false,
  "isLocked": false,
  "isVisible": true,
  "layerListExpandedType": 0,
  "name": "Path",
  "nameIsFixed": false,
  "path": {
    "_class": "path",
    "isClosed": true,
    "pointRadiusBehaviour": 1,
    "points": [
      {
        "_class": "curvePoint",
        "cornerRadius": 0,
        "curveFrom": "{0, 1}",
        "curveMode": 1,
        "curveTo": "{0, 1}",
        "hasCurveFrom": false,
        "hasCurveTo": false,
        "point": "{0, 1}"
      },
      {
        "_class": "curvePoint",
        "cornerRadius": 0,
        "curveFrom": "{0, 0}",
        "curveMode": 1,
        "curveTo": "{0, 0}",
        "hasCurveFrom": false,
        "hasCurveTo": false,
        "point": "{0, 0}"
      },
      {
        "_class": "curvePoint",
        "cornerRadius": 0,
        "curveFrom": "{0.28060010503544475, 0}",
        "curveMode": 1,
        "curveTo": "{0.28060010503544475, 0}",
        "hasCurveFrom": false,
        "hasCurveTo": false,
        "point": "{0.28060010503544475, 0}"
      },
      {
        "_class": "curvePoint",
        "cornerRadius": 0,
        "curveFrom": "{0.28060010503544475, 0.38230305811440568}",
        "curveMode": 1,
        "curveTo": "{0.28060010503544475, 0.38230305811440568}",
        "hasCurveFrom": false,
        "hasCurveTo": false,
        "point": "{0.28060010503544475, 0.38230305811440568}"
      },
      {
        "_class": "curvePoint",
        "cornerRadius": 0,
        "curveFrom": "{0.71939989496455548, 0.38230305811440568}",
        "curveMode": 1,
        "curveTo": "{0.71939989496455548, 0.38230305811440568}",
        "hasCurveFrom": false,
        "hasCurveTo": false,
        "point": "{0.71939989496455548, 0.38230305811440568}"
      },
      {
        "_class": "curvePoint",
        "cornerRadius": 0,
        "curveFrom": "{0.71939989496455548, 0}",
        "curveMode": 1,
        "curveTo": "{0.71939989496455548, 0}",
        "hasCurveFrom": false,
        "hasCurveTo": false,
        "point": "{0.71939989496455548, 0}"
      },
      {
        "_class": "curvePoint",
        "cornerRadius": 0,
        "curveFrom": "{1, 0}",
        "curveMode": 1,
        "curveTo": "{1, 0}",
        "hasCurveFrom": false,
        "hasCurveTo": false,
        "point": "{1, 0}"
      },
      {
        "_class": "curvePoint",
        "cornerRadius": 0,
        "curveFrom": "{1, 1}",
        "curveMode": 1,
        "curveTo": "{1, 1}",
        "hasCurveFrom": false,
        "hasCurveTo": false,
        "point": "{1, 1}"
      },
      {
        "_class": "curvePoint",
        "cornerRadius": 0,
        "curveFrom": "{0.71939989496455548, 1}",
        "curveMode": 1,
        "curveTo": "{0.71939989496455548, 1}",
        "hasCurveFrom": false,
        "hasCurveTo": false,
        "point": "{0.71939989496455548, 1}"
      },
      {
        "_class": "curvePoint",
        "cornerRadius": 0,
        "curveFrom": "{0.71939989496455548, 0.59050164486433365}",
        "curveMode": 1,
        "curveTo": "{0.71939989496455548, 0.59050164486433365}",
        "hasCurveFrom": false,
        "hasCurveTo": false,
        "point": "{0.71939989496455548, 0.59050164486433365}"
      },
      {
        "_class": "curvePoint",
        "cornerRadius": 0,
        "curveFrom": "{0.28060010503544475, 0.59050164486433365}",
        "curveMode": 1,
        "curveTo": "{0.28060010503544475, 0.59050164486433365}",
        "hasCurveFrom": false,
        "hasCurveTo": false,
        "point": "{0.28060010503544475, 0.59050164486433365}"
      },
      {
        "_class": "curvePoint",
        "cornerRadius": 0,
        "curveFrom": "{0.28060010503544475, 1}",
        "curveMode": 1,
        "curveTo": "{0.28060010503544475, 1}",
        "hasCurveFrom": false,
        "hasCurveTo": false,
        "point": "{0.28060010503544475, 1}"
      }
    ]
  },
  "resizingConstraint": 63,
  "resizingType": 0,
  "rotation": 0,
  "shouldBreakMaskChain": false
}